README.md
setup.py
uname2.py
uname2.egg-info/PKG-INFO
uname2.egg-info/SOURCES.txt
uname2.egg-info/dependency_links.txt
uname2.egg-info/entry_points.txt
uname2.egg-info/requires.txt
uname2.egg-info/top_level.txt